.gitignore
LICENSE
MANIFEST.in
README.md
earth-sunset.png
setup.py
rainbow_connection.egg-info/PKG-INFO
rainbow_connection.egg-info/SOURCES.txt
rainbow_connection.egg-info/dependency_links.txt
rainbow_connection.egg-info/not-zip-safe
rainbow_connection.egg-info/requires.txt
rainbow_connection.egg-info/top_level.txt
rainbowconnection/__init__.py
rainbowconnection/animatetools.py
rainbowconnection/colortools.py
rainbowconnection/imports.py
rainbowconnection/plottingtools.py
rainbowconnection/resampletools.py
rainbowconnection/units.py
rainbowconnection/version.py
rainbowconnection/atmospheres/__init__.py
rainbowconnection/atmospheres/atmosphere.py
rainbowconnection/atmospheres/earth.py
rainbowconnection/atmospheres/exoplanet.py
rainbowconnection/atmospheres/hotjupiter.py
rainbowconnection/atmospheres/noatmosphere.py
rainbowconnection/atmospheres/sky.py
rainbowconnection/atmospheres/sunset.py
rainbowconnection/data/earthtransmission.txt
rainbowconnection/data/solarspectrum.txt
rainbowconnection/data/fortney/README.txt
rainbowconnection/data/fortney/lambda_1500K_g10_noTiOVO.dat
rainbowconnection/data/fortney/lambda_1500K_g10_wTiOVO.dat
rainbowconnection/sources/__init__.py
rainbowconnection/sources/blank.py
rainbowconnection/sources/lightbulbs.py
rainbowconnection/sources/planck.py
rainbowconnection/sources/spectra.py
rainbowconnection/sources/star.py
rainbowconnection/sources/sun.py
rainbowconnection/tests/__init__.py
rainbowconnection/tests/directory.py
rainbowconnection/tests/test_atmospheres.py
rainbowconnection/tests/test_lights.py
rainbowconnection/tests/test_plots.py
rainbowconnection/tests/test_resampling.py
rainbowconnection/tests/test_sunsets.py